README.md
setup.cfg
setup.py
keycloak/__init__.py
keycloak/connection.py
keycloak/exceptions.py
keycloak/keycloak_admin.py
keycloak/keycloak_openid.py
keycloak/urls_patterns.py
keycloak/authorization/__init__.py
keycloak/authorization/permission.py
keycloak/authorization/policy.py
keycloak/authorization/role.py
keycloak/tests/__init__.py
keycloak/tests/test_connection.py
keycloak_client.egg-info/PKG-INFO
keycloak_client.egg-info/SOURCES.txt
keycloak_client.egg-info/dependency_links.txt
keycloak_client.egg-info/requires.txt
keycloak_client.egg-info/top_level.txt