Metadata-Version: 1.1
Name: keycloak-client
Version: 0.15.3
Summary: keycloak-client(fork from python-keycloak) is a Python package providing access to the Keycloak API.
Home-page: https://github.com/ly798/python-keycloak.git
Author: liuyang
Author-email: liuyang@gmail.com
License: The MIT License
Keywords: keycloak openid
Platform: UNKNOWN
Classifier: Programming Language :: Python :: 3
Classifier: License :: OSI Approved :: MIT License
Classifier: Development Status :: 3 - Alpha
Classifier: Operating System :: MacOS
Classifier: Operating System :: Unix
Classifier: Operating System :: Microsoft :: Windows
Classifier: Topic :: Utilities
